nuitrcs_example/__init__.py
nuitrcs_example/pipeline.py
nuitrcs_example/mymodule/__init__.py
nuitrcs_example/mymodule/mymodule.py
nuitrcs_example-1.0.0.dist-info/LICENSE
nuitrcs_example-1.0.0.dist-info/METADATA
nuitrcs_example-1.0.0.dist-info/WHEEL
nuitrcs_example-1.0.0.dist-info/entry_points.txt
nuitrcs_example-1.0.0.dist-info/top_level.txt
nuitrcs_example-1.0.0.dist-info/RECORD
