Metadata-Version: 2.1
Name: nuitrcs-example
Version: 1.0.0
Summary: NUITRCS GitHub Actions Workshop
Author-email: Scott Coughlin <s-coughlin@northwestern.edu>
Maintainer-email: Scott Coughlin <s-coughlin@northwestern.edu>
License: GNU GENERAL PUBLIC LICENSE
Project-URL: Homepage, https://github.com/nuitrcs/rcds-gh-actions-workshop
Keywords: nuitrcs
Classifier: Development Status :: 3 - Alpha
Classifier: Intended Audience :: Developers
Classifier: Topic :: Software Development :: Build Tools
Classifier: License :: OSI Approved :: GNU General Public License v3 or later (GPLv3+)
Classifier: Programming Language :: Python :: 3
Classifier: Programming Language :: Python :: 3.8
Classifier: Programming Language :: Python :: 3.9
Classifier: Programming Language :: Python :: 3.10
Classifier: Programming Language :: Python :: 3.11
Classifier: Programming Language :: Python :: 3 :: Only
Requires-Python: >3.7
License-File: LICENSE
Requires-Dist: numpy
Provides-Extra: dev
Requires-Dist: check-manifest ; extra == 'dev'
Provides-Extra: doc
Requires-Dist: matplotlib ; extra == 'doc'
Requires-Dist: ipython ; extra == 'doc'
Requires-Dist: sphinx ; extra == 'doc'
Requires-Dist: numpydoc ; extra == 'doc'
Requires-Dist: sphinx-rtd-theme ; extra == 'doc'
Requires-Dist: sphinxcontrib-programoutput ; extra == 'doc'
Provides-Extra: test
Requires-Dist: coverage ; extra == 'test'
